loopfinder/__init__.py
loopfinder/_version.py
loopfinder/motion.py
loopfinder/utils.py
loopfinder/vision.py
loopfinder-3.0.1.dist-info/licenses/LICENSE
loopfinder-3.0.1.dist-info/METADATA
loopfinder-3.0.1.dist-info/WHEEL
loopfinder-3.0.1.dist-info/top_level.txt
loopfinder-3.0.1.dist-info/RECORD
