Metadata-Version: 2.4
Name: loopfinder
Version: 3.0.1
Summary: A library for loop centring in MX crystallography
Home-page: https://gitlab.maxiv.lu.se/kits-maxiv/lib-maxiv-loopfinder
Author: KITS
Author-email: isak.lindhe@maxiv.lu.se
License: GPL-3.0-or-later
Requires-Python: >=3.10
License-File: LICENSE
Requires-Dist: opencv-python-headless
Requires-Dist: numpy
Provides-Extra: tests
Requires-Dist: pytest; extra == "tests"
Requires-Dist: pytest-cov; extra == "tests"
Dynamic: author
Dynamic: author-email
Dynamic: home-page
Dynamic: license
Dynamic: license-file
Dynamic: provides-extra
Dynamic: requires-dist
Dynamic: requires-python
Dynamic: summary
